{
  "title": "Mälaren",
  "slug": "malaren",
  "description": "Storstadsnära fiske med storvuxen gädda, abborre och gös inom räckhåll från Stockholm.",
  "heroImage": "/images/destinations/malaren.jpg",
  "lat": 59.5,
  "lng": 17.1,
  "län": "Stockholm / Södermanland / Västmanland",
  "primarySpecies": ["gädda", "abborre", "gös"],
  "waterType": "lake",
  "iFiskeUrl": "https://ifiske.se/fiske/malaren.htm",
  "recommendedGear": ["berkley-maxfire-pike", "savage-gear-sg2-pike", "garmin-striker-4"],
  "content": "Mälaren är Stockholmsregionens stora fiskevatten, en labyrint av vikar, sund och öar som sträcker sig 120 kilometer västerut från Stockholms innerstad. Sjön delas av broar och sund i tre stora bassänger, var och en med sin karaktär och sina fiskbestånd. Den östra delen, närmast Stockholm, är kanske den mest intensivt fiskade men också den mest tillgängliga. Gäddfisket i Mälaren är legendariskt bland Stockholms sportfiskare. Vassbälten längs Ekerön och ut mot Björkfjärden håller fisk hela säsongen, men det är i maj och september som de riktigt stora exemplaren är aktiva. En Mälarengädda på tio kilo är realistisk för den som kan sin biologi och arbetar rätt marker vid rätt tid. Abborrfisket gynnas av sjöns variation. I de grunda vikarna med hård bottenbotten hittar du abborren på hårt jiggat fiske, medan de djupare bassängerna kräver mer sofistikerade presentationer. Gösen etablerade sig i Mälaren på allvar under 1990-talet och har sedan dess blivit ett av regionens mest eftertraktade sportfisken. Fiska längs kanter och i utloppssund under gryning och skymning för de bästa resultaten. En båt öppnar upp möjligheterna dramatiskt, men Mälaren erbjuder också utmärkta möjligheter för den bryggan- eller strandfiskaren.",
  "publishedAt": "2025-05-10",
  "updatedAt": "2026-02-01"
}
